m_test_v10-0.1.2.dist-info/METADATA
m_test_v10-0.1.2.dist-info/WHEEL
m_test_v10-0.1.2.dist-info/entry_points.txt
m_test_v10/__init__.py
m_test_v10-0.1.2.dist-info/RECORD
