Metadata-Version: 2.1
Name: m-test-v10
Version: 0.1.2
Summary: Default template for PDM package
Author-Email: lwmacct <lwmacct@icloud.com>
License: MIT
Requires-Python: >=3.12
